ptools/__init__.py
new_ptools-0.1.0.dist-info/METADATA
new_ptools-0.1.0.dist-info/WHEEL
new_ptools-0.1.0.dist-info/top_level.txt
new_ptools-0.1.0.dist-info/RECORD
